fixtures_extractor/__init__.py
fixtures_extractor/apps.py
fixtures_extractor/dtos.py
fixtures_extractor/encoders.py
fixtures_extractor/enums.py
fixtures_extractor/extra_logging_formatter.py
fixtures_extractor/orm_extractor.py
fixtures_extractor/management/__init__.py
fixtures_extractor/management/commands/__init__.py
fixtures_extractor/management/commands/extract_fixture.py
django_fixtures_extractor-0.1.3.dist-info/LICENSE
django_fixtures_extractor-0.1.3.dist-info/WHEEL
django_fixtures_extractor-0.1.3.dist-info/METADATA
django_fixtures_extractor-0.1.3.dist-info/RECORD
